MANIFEST.in
setup.py
rest_framework_swagger_zl/README.md
rest_framework_swagger_zl/__init__.py
rest_framework_swagger_zl/renderers.py
rest_framework_swagger_zl/settings.py
rest_framework_swagger_zl/views.py
rest_framework_swagger_zl.egg-info/PKG-INFO
rest_framework_swagger_zl.egg-info/SOURCES.txt
rest_framework_swagger_zl.egg-info/dependency_links.txt
rest_framework_swagger_zl.egg-info/top_level.txt
rest_framework_swagger_zl/static/rest_framework_swagger/favicon-16x16.png
rest_framework_swagger_zl/static/rest_framework_swagger/favicon-32x32.png
rest_framework_swagger_zl/static/rest_framework_swagger/logo_small.png
rest_framework_swagger_zl/static/rest_framework_swagger/bundles/app.bundle.css
rest_framework_swagger_zl/static/rest_framework_swagger/bundles/app.bundle.js
rest_framework_swagger_zl/static/rest_framework_swagger/bundles/vendors.bundle.css
rest_framework_swagger_zl/static/rest_framework_swagger/bundles/vendors.bundle.js
rest_framework_swagger_zl/templates/rest_framework_swagger/index.html